recmetrics_pyspark/__init__.py
recmetrics_pyspark/recmetrics_pyspark.py
recmetrics_pyspark-0.0.1.dist-info/LICENSE
recmetrics_pyspark-0.0.1.dist-info/METADATA
recmetrics_pyspark-0.0.1.dist-info/WHEEL
recmetrics_pyspark-0.0.1.dist-info/top_level.txt
recmetrics_pyspark-0.0.1.dist-info/RECORD
