Metadata-Version: 2.1
Name: recmetrics-pyspark
Version: 0.0.1
Summary: A library of recommender systems metrics for big data
Home-page: https://github.com/camiloakv/recmetrics-pyspark
Author: Camilo Akimushkin Valencia
Author-email: camilo.akimushkin@gmail.com
Classifier: Programming Language :: Python :: 3
Classifier: License :: OSI Approved :: MIT License
Classifier: Operating System :: OS Independent
License-File: LICENSE
